LICENSE
MANIFEST.in
README.md
setup.cfg
setup.py
tests/__init__.py
tests/note_test.py
tnote/__init__.py
tnote/__main__.py
tnote/func_module.py
tnote/note_module.py
tnote_cli.egg-info/PKG-INFO
tnote_cli.egg-info/SOURCES.txt
tnote_cli.egg-info/dependency_links.txt
tnote_cli.egg-info/entry_points.txt
tnote_cli.egg-info/requires.txt
tnote_cli.egg-info/top_level.txt