Metadata-Version: 2.1
Name: tnote-cli
Version: 0.0.6
Summary: A simple Terminal-based notes app
Home-page: https://github.com/CarsonHenrich/tnote-cli
Author: Carson Henrich
Author-email: contact@carsonhenrich.com
License: MIT
Project-URL: github, https://github.com/carsonhenrich/tnote-cli
Classifier: Environment :: Console
Classifier: Development Status :: 2 - Pre-Alpha
Classifier: Intended Audience :: Developers
Classifier: Intended Audience :: System Administrators
Classifier: Intended Audience :: Information Technology
Classifier: Programming Language :: Python :: 3
Classifier: License :: OSI Approved :: MIT License 
Classifier: Operating System :: MacOS
Classifier: Operating System :: POSIX
Classifier: Natural Language :: English
Classifier: Topic :: Utilities
License-File: LICENSE
